{
  "main": {
    "id": "5ce91c439da39b6b",
    "type": "split",
    "children": [
      {
        "id": "b33cf28c56e20c8c",
        "type": "tabs",
        "children": [
          {
            "id": "6b4a6cd99e2171cd",
            "type": "leaf",
            "state": {
              "type": "markdown",
              "state": {
                "file": "_posts/2025-03-26-Crypto-RSA(二).md",
                "mode": "source",
                "source": false,
                "backlinks": true,
                "backlinkOpts": {
                  "collapseAll": false,
                  "extraContext": false,
                  "sortOrder": "alphabetical",
                  "showSearch": false,
                  "searchQuery": "",
                  "backlinkCollapsed": false,
                  "unlinkedCollapsed": true
                }
              },
              "icon": "lucide-file",
              "title": "2025-03-26-Crypto-RSA(二)"
            }
          }
        ]
      }
    ],
    "direction": "vertical"
  },
  "left": {
    "id": "648b42f0ad50a91a",
    "type": "mobile-drawer",
    "children": [
      {
        "id": "4e9cb6be9f7d94b9",
        "type": "leaf",
        "state": {
          "type": "file-explorer",
          "state": {
            "sortOrder": "alphabetical",
            "autoReveal": false
          },
          "icon": "lucide-folder-closed",
          "title": "文件列表"
        }
      },
      {
        "id": "6070f1135667c0d8",
        "type": "leaf",
        "state": {
          "type": "search",
          "state": {
            "query": "",
            "matchingCase": false,
            "explainSearch": false,
            "collapseAll": false,
            "extraContext": false,
            "sortOrder": "alphabetical"
          },
          "icon": "lucide-search",
          "title": "搜索"
        }
      },
      {
        "id": "e518eed3e3b24b1a",
        "type": "leaf",
        "state": {
          "type": "tag",
          "state": {
            "sortOrder": "frequency",
            "useHierarchy": true,
            "showSearch": false,
            "searchQuery": ""
          },
          "icon": "lucide-tags",
          "title": "标签"
        }
      },
      {
        "id": "f03e525555432782",
        "type": "leaf",
        "state": {
          "type": "bookmarks",
          "state": {},
          "icon": "lucide-bookmark",
          "title": "书签"
        }
      }
    ],
    "currentTab": 0
  },
  "right": {
    "id": "f35cc22f51d6f7a9",
    "type": "mobile-drawer",
    "children": [
      {
        "id": "4f1a848a17823e9c",
        "type": "leaf",
        "state": {
          "type": "backlink",
          "state": {
            "file": "_posts/2025-03-23-Crypto-RSA(一).md",
            "collapseAll": false,
            "extraContext": false,
            "sortOrder": "alphabetical",
            "showSearch": false,
            "searchQuery": "",
            "backlinkCollapsed": false,
            "unlinkedCollapsed": true
          },
          "icon": "links-coming-in",
          "title": "反向链接"
        }
      },
      {
        "id": "b490e61d3b5dfba8",
        "type": "leaf",
        "state": {
          "type": "outgoing-link",
          "state": {
            "file": "_posts/2025-03-23-Crypto-RSA(一).md",
            "linksCollapsed": false,
            "unlinkedCollapsed": true
          },
          "icon": "links-going-out",
          "title": "出链"
        }
      },
      {
        "id": "c86c0ad6c373c51b",
        "type": "leaf",
        "state": {
          "type": "outline",
          "state": {
            "file": "_posts/2025-03-23-Crypto-RSA(一).md",
            "followCursor": false,
            "showSearch": false,
            "searchQuery": ""
          },
          "icon": "lucide-list",
          "title": "大纲"
        }
      }
    ],
    "currentTab": 0
  },
  "left-ribbon": {
    "hiddenItems": {
      "switcher:打开快速切换": false,
      "graph:查看关系图谱": false,
      "canvas:新建白板": false,
      "daily-notes:打开/创建今天的日记": false,
      "templates:插入模板": false,
      "command-palette:打开命令面板": false
    }
  },
  "active": "6b4a6cd99e2171cd",
  "lastOpenFiles": [
    "_posts/2025-03-23-Crypto-RSA(一).md",
    "_site/package.json",
    "_site/package-lock.json",
    "package.json",
    "package-lock.json",
    "node_modules/monokai/hyperterm-monokai/index.js",
    "node_modules/monokai/hyperterm-monokai/README.md",
    "node_modules/monokai/hyperterm-monokai/package.json",
    "node_modules/monokai/hyperterm-monokai",
    "node_modules/monokai/package.json",
    "node_modules/monokai",
    "node_modules",
    "index.md",
    "_posts/2025-03-26-Crypto-RSA(二).md",
    "2025-03-23-Crypto-RSA(一).md",
    "[[2025-03-23-Crypto-RSA(一)]].md",
    "2025-03-26-Crypto-RSA(二) 1.md",
    "2025-03-26-Crypto-RSA(二).md",
    "about.md",
    "_site/[[2025-03-23-Crypto-RSA(一)]].md"
  ]
}